example_package/__init__.py
example_package/example.py
tryout-0.0.1.dist-info/LICENSE
tryout-0.0.1.dist-info/METADATA
tryout-0.0.1.dist-info/WHEEL
tryout-0.0.1.dist-info/top_level.txt
tryout-0.0.1.dist-info/RECORD
